ethiopian_date_converter/__init__.py
ethiopian_date_converter/ethiopian_date_convertor.py
py_ethiopian_date_converter-0.1.0.dist-info/LICENSE
py_ethiopian_date_converter-0.1.0.dist-info/METADATA
py_ethiopian_date_converter-0.1.0.dist-info/WHEEL
py_ethiopian_date_converter-0.1.0.dist-info/top_level.txt
py_ethiopian_date_converter-0.1.0.dist-info/RECORD
