Metadata-Version: 2.2
Name: py-ethiopian-date-converter
Version: 0.1.0
Summary: A Python package to convert dates between Gregorian and Ethiopian calendars.
Home-page: https://github.com/GutemaG/py_ethiopain_date_converter
Author: Birhanu Gudisa
Author-email: bir13gud17@gmail.com
Classifier: Programming Language :: Python :: 3
Classifier: License :: OSI Approved :: MIT License
Classifier: Operating System :: OS Independent
Requires-Python: >=3.6
License-File: LICENSE
Dynamic: author
Dynamic: author-email
Dynamic: classifier
Dynamic: description
Dynamic: description-content-type
Dynamic: home-page
Dynamic: requires-python
Dynamic: summary
